ddbcache.py
ddb_cache-0.6.0.dist-info/WHEEL
ddb_cache-0.6.0.dist-info/METADATA
ddb_cache-0.6.0.dist-info/license_files/LICENSE
ddb_cache-0.6.0.dist-info/RECORD
