Metadata-Version: 2.1
Name: ddb-cache
Version: 0.6.0
Summary: A simple interface for caching items in DynamoDB
License: LGPL-3.0-or-later
Author-email: Sam <dev@samarthj.com>
Requires-Python: >=3.9
Classifier: Development Status :: 4 - Beta
Classifier: Environment :: Web Environment
Classifier: Intended Audience :: Developers
Classifier: License :: OSI Approved :: GNU Lesser General Public License v3 or later (LGPLv3+)
Classifier: Natural Language :: English
Classifier: Operating System :: OS Independent
Classifier: Programming Language :: Python :: 3
Classifier: Programming Language :: Python :: 3 :: Only
Classifier: Programming Language :: Python :: 3.10
Classifier: Programming Language :: Python :: 3.9
Classifier: Topic :: Database
Classifier: Topic :: Database :: Front-Ends
Classifier: Topic :: Software Development :: Libraries :: Python Modules
Classifier: Topic :: Utilities
Requires-Dist: boto3; python_version>='3.9'
Requires-Dist: pylib-helpers; python_version>='3.9'
Project-URL: Bug Tracker, https://github.com/samarthj/py-ddbcache/issues
Project-URL: Changelog, https://github.com/samarthj/py-ddbcache/blob/main/CHANGELOG.md
Project-URL: Documentation, https://github.com/samarthj/py-ddbcache/blob/main/README.md
Project-URL: Repository, https://github.com/samarthj/py-ddbcache
